tykes/__init__.py
tykes/__main__.py
tykes/cli.py
tykes/color.py
tykes/farkle/__init__.py
tykes/farkle/main.py
tykes/farkle/utils.py
tykes/flood/__init__.py
tykes/flood/main.py
tykes/maze.py
tykes/memory.py
tykes/utils.py
tykes-1.0.0.dist-info/LICENSE
tykes-1.0.0.dist-info/WHEEL
tykes-1.0.0.dist-info/METADATA
tykes-1.0.0.dist-info/RECORD
